django_eventspipe/__init__.py
django_eventspipe/admin.py
django_eventspipe/apps.py
django_eventspipe/decorators.py
django_eventspipe/exceptions.py
django_eventspipe/schedulers.py
django_eventspipe/signals.py
django_eventspipe/tasks.py
django_eventspipe/tests.py
django_eventspipe/urls.py
django_eventspipe/utils.py
django_eventspipe/validators.py
django_eventspipe/views.py
django_eventspipe/migrations/0001_initial.py
django_eventspipe/migrations/__init__.py
django_eventspipe/models/__init__.py
django_eventspipe/models/artifact.py
django_eventspipe/models/event_schedule.py
django_eventspipe/models/pipeline.py
django_eventspipe/models/pipeline_artifact.py
django_eventspipe/models/pipeline_definition.py
django_eventspipe/models/pipeline_definition_task_definition.py
django_eventspipe/models/task.py
django_eventspipe/models/task_definition.py
django_eventspipe-0.1.1b1.dist-info/licenses/LICENSE.txt
django_eventspipe-0.1.1b1.dist-info/METADATA
django_eventspipe-0.1.1b1.dist-info/WHEEL
django_eventspipe-0.1.1b1.dist-info/top_level.txt
django_eventspipe-0.1.1b1.dist-info/RECORD
