Metadata-Version: 2.4
Name: django-eventspipe
Version: 0.1.1b1
Summary: TODO
Author-email: Giuseppe Corti <giuseppe.corti@pm.me>
Project-URL: Homepage, https://github.com/r3vn/django-eventspipe
Project-URL: Issues, https://github.com/r3vn/django-eventspipe/issues
Classifier: Environment :: Web Environment
Classifier: Intended Audience :: Developers
Classifier: License :: OSI Approved :: MIT License
Classifier: Operating System :: OS Independent
Classifier: Programming Language :: Python :: 3 :: Only
Classifier: Programming Language :: Python :: 3.11
Classifier: Programming Language :: Python :: 3.12
Classifier: Programming Language :: Python :: Implementation :: CPython
Classifier: Topic :: Software Development :: Libraries :: Application Frameworks
Classifier: Topic :: Software Development :: Libraries :: Python Modules
Requires-Python: >=3.11
License-File: LICENSE.txt
Requires-Dist: django>=5.0
Requires-Dist: celery>=5.4
Requires-Dist: python-crontab>=2.3.4
Dynamic: license-file
